{
  "point": [
    {
      "user": "280753236548386816",
      "point": 998912
    },
    {
      "user": "398646646893838349",
      "point": 30
    },
    {
      "user": "332254767760015372",
      "point": 70
    },
    {
      "user": "372104607389843457",
      "point": 50
    },
    {
      "user": "385440331430232074",
      "point": 20
    },
    {
      "user": "318723824839294977",
      "point": 81
    },
    {
      "user": "344967667603734529",
      "point": 27
    },
    {
      "user": "323920342324215809",
      "point": 80
    },
    {
      "user": "335488225487486976",
      "point": 40
    },
    {
      "user": "314509226720362505",
      "point": 9
    },
    {
      "user": "336560869708398594",
      "point": 10
    },
    {
      "user": "398608472612012034",
      "point": 10
    }
  ],
  "Inventory": []
